{"cameraMode":{"drawMode":0,"name":"Shaded","section":"Shading Mode"},"sceneLighting":true,"audioPlay":false,"sceneViewState":{"m_AlwaysRefresh":false,"showFog":true,"showSkybox":true,"showFlares":true,"showImageEffects":true,"showParticleSystems":true,"showVisualEffectGraphs":true,"m_FxEnabled":true},"in2DMode":false,"pivot":{"x":5.893911361694336,"y":0.3124046325683594,"z":-4.18310022354126},"rotation":{"x":-0.0240092221647501,"y":0.9759070873260498,"z":-0.14631050825119019,"w":-0.16041061282157899},"size":3.079942464828491,"orthographic":false}